gmatpyplus/__init__.py
gmatpyplus/api_funcs.py
gmatpyplus/basics.py
gmatpyplus/burn.py
gmatpyplus/commands.py
gmatpyplus/executive.py
gmatpyplus/gmatpy_classes.txt
gmatpyplus/hardware.py
gmatpyplus/interpreter.py
gmatpyplus/load_gmat.py
gmatpyplus/orbit.py
gmatpyplus/parameter.py
gmatpyplus/solver.py
gmatpyplus/spacecraft.py
gmatpyplus/utils.py
gmatpyplus-0.10.3.dist-info/METADATA
gmatpyplus-0.10.3.dist-info/WHEEL
gmatpyplus-0.10.3.dist-info/licenses/LICENSE
gmatpyplus-0.10.3.dist-info/RECORD
