Metadata-Version: 2.4
Name: gmatpyplus
Version: 0.10.3
Summary: An extra wrapper for the GMAT Python API to simplify setting up mission simulations.
Project-URL: Homepage, https://github.com/weasdown/gmatpyplus
Project-URL: source_archive, https://github.com/weasdown/gmatpyplus/releases
Project-URL: Issues, https://github.com/weasdown/gmatpyplus/issues/
Author-email: William Easdown Babb <weasdown99@gmail.com>
License-Expression: MIT
License-File: LICENSE
Classifier: Development Status :: 3 - Alpha
Classifier: Intended Audience :: Developers
Classifier: Operating System :: OS Independent
Classifier: Programming Language :: Python :: 3
Classifier: Programming Language :: Python :: 3.9
Classifier: Programming Language :: Python :: 3.10
Classifier: Programming Language :: Python :: 3.11
Classifier: Programming Language :: Python :: 3.12
Classifier: Programming Language :: Python :: 3.13
Classifier: Programming Language :: Python :: 3.14
Requires-Python: >=3.9
Requires-Dist: numpy>2.0.0
